Workbook

Sheet Leeme
A1: Field Kit - Piloto Cognitivo Lexical es-CO - O*NET Interest Profiler Short Form
A2: Plantillas de trabajo. Version 1.0 - 2026-05-23. Acompana al documento .md del field kit.
A4: AVISO | B4: Este libro NO contiene datos. Son plantillas vacias para que un equipo humano ejecute el piloto. Las celdas con fondo amarillo se llenan en campo / analisis.
A5: Hoja Cuotas | B5: Matriz de cuotas estratificadas. Conteos automaticos contra la hoja Reclutamiento.
A6: Hoja Reclutamiento | B6: Una fila por contacto del screener. Clasificar ciudad y educacion con los valores exactos de las listas.
A7: Hoja Captura_plantilla | B7: Plantilla de captura por item (60 filas). DUPLICAR esta hoja una vez por participante; renombrar con el ID.
A8: Hoja Codebook | B8: Definiciones de codigos para los 2 codificadores. Hoja de referencia, no se llena.
A9: Hoja Log_cambios | B9: Log de cambios pack 8.4. Pre-cargado con las 24 propuestas a priori del desk review (Parte B).
A10: Hoja Metricas_item | B10: 60 items. Metricas de comprension por item; se llenan tras codificar (plan de analisis A-8).
A11: Hoja Metricas_dimension | B11: 6 dimensiones RIASEC. Alfa provisional y comprension media; se llenan tras el analisis.
A12: Quien llena que | B12: Reclutamiento: equipo de reclutamiento. Captura: facilitacion. Codigos: 2 codificadores. Metricas y Log post-piloto: analisis.
A13: No fabricar datos | B13: Las metricas (alfa, % comprension, tiempos) solo se llenan con datos reales de campo. Ver AVISO DE ALCANCE del .md.

Sheet Cuotas
A1: Matriz de cuotas estratificadas - meta de analisis N=36 (reclutar 40)
A3: Ciudad (grupo) | B3: Educacion | C3: Meta | D3: Reclutados (auto) | E3: Faltan (auto)
A4: Bogota | B4: Secundaria | C4: 6 | D4: =COUNTIFS(Reclutamiento!C:C,A4,Reclutamiento!D:D,B4,Reclutamiento!J:J,"Reclutado") -> 0 | E4: =C4-D4 -> 6
A5: Bogota | B5: Tecnico-tecnologico | C5: 6 | D5: =COUNTIFS(Reclutamiento!C:C,A5,Reclutamiento!D:D,B5,Reclutamiento!J:J,"Reclutado") -> 0 | E5: =C5-D5 -> 6
A6: Bogota | B6: Universitario | C6: 6 | D6: =COUNTIFS(Reclutamiento!C:C,A6,Reclutamiento!D:D,B6,Reclutamiento!J:J,"Reclutado") -> 0 | E6: =C6-D6 -> 6
A7: Medellin / Cali | B7: Secundaria | C7: 3 | D7: =COUNTIFS(Reclutamiento!C:C,A7,Reclutamiento!D:D,B7,Reclutamiento!J:J,"Reclutado") -> 0 | E7: =C7-D7 -> 3
A8: Medellin / Cali | B8: Tecnico-tecnologico | C8: 3 | D8: =COUNTIFS(Reclutamiento!C:C,A8,Reclutamiento!D:D,B8,Reclutamiento!J:J,"Reclutado") -> 0 | E8: =C8-D8 -> 3
A9: Medellin / Cali | B9: Universitario | C9: 3 | D9: =COUNTIFS(Reclutamiento!C:C,A9,Reclutamiento!D:D,B9,Reclutamiento!J:J,"Reclutado") -> 0 | E9: =C9-D9 -> 3
A10: Otras ciudades | B10: Secundaria | C10: 3 | D10: =COUNTIFS(Reclutamiento!C:C,A10,Reclutamiento!D:D,B10,Reclutamiento!J:J,"Reclutado") -> 0 | E10: =C10-D10 -> 3
A11: Otras ciudades | B11: Tecnico-tecnologico | C11: 3 | D11: =COUNTIFS(Reclutamiento!C:C,A11,Reclutamiento!D:D,B11,Reclutamiento!J:J,"Reclutado") -> 0 | E11: =C11-D11 -> 3
A12: Otras ciudades | B12: Universitario | C12: 3 | D12: =COUNTIFS(Reclutamiento!C:C,A12,Reclutamiento!D:D,B12,Reclutamiento!J:J,"Reclutado") -> 0 | E12: =C12-D12 -> 3
A13: TOTAL | C13: =SUM(C4:C12) -> 36 | D13: =SUM(D4:D12) -> 0 | E13: =SUM(E4:E12) -> 36
A15: Genero objetivo 50/50 y franjas de edad (18-25 / 26-40 / 41-55) se balancean dentro de las celdas; ver hoja Reclutamiento.

Sheet Reclutamiento
A1: Salida del screener - una fila por contacto
A3: ID | B3: Ciudad (texto libre) | C3: Ciudad (grupo) | D3: Educacion | E3: Genero | F3: Edad | G3: Apto think-aloud | H3: Elegible VIA | I3: Elegible NFR-27/28 | J3: Estado | K3: Motivo exclusion
A49: Valores Ciudad (grupo): Bogota | Medellin / Cali | Otras ciudades. Educacion: Secundaria | Tecnico-tecnologico | Universitario. Estado: Reclutado | Lista de espera | Excluido.

Sheet Captura_plantilla
A1: Hoja de captura por item - DUPLICAR una por participante
A2: ID participante | D2: Fecha
A3: Facilitador/a | D3: Codificador/a 1
A4: Codificador/a 2 | D4: Ciudad / celda
A5: Educacion | D5: Genero
A6: Edad | D6: Version es-CO usada
A7: Subsets (NFR / VIA)
A8: item_id | B8: dim | C8: texto_presentado | D8: tiempo_resp_seg | E8: reformulo (si/no) | F8: pidio_aclaracion (si/no) | G8: senal_no_comprension (si/no) | H8: marca_ajeno (si/no) | I8: discrepancia (si/no) | J8: respuesta_escala (0-4) | K8: palabras_senal | L8: comentarios | M8: codigo_1 | N8: codigo_2 | O8: codigo_consenso
A9: R1 | B9: R | C9: Construir gabinetes de cocina
A10: R2 | B10: R | C10: Colocar ladrillos o baldosas
A11: R3 | B11: R | C11: Reparar electrodomesticos
A12: R4 | B12: R | C12: Criar peces en un criadero
A13: R5 | B13: R | C13: Ensamblar partes electronicas
A14: R6 | B14: R | C14: Manejar un camion para entregar paquetes a oficinas y casas
A15: R7 | B15: R | C15: Probar la calidad de las piezas antes del envio
A16: R8 | B16: R | C16: Reparar e instalar cerraduras
A17: R9 | B17: R | C17: Poner a punto y operar maquinas para fabricar productos
A18: R10 | B18: R | C18: Apagar incendios forestales
A19: I1 | B19: I | C19: Desarrollar un medicamento nuevo
A20: I2 | B20: I | C20: Estudiar formas de reducir la contaminacion del agua
... A68: C10 | B68: C | C68: Sellar, clasificar y distribuir el correo de una organizacion
A70: texto_presentado: ajustar al texto es-CO realmente mostrado en pantalla (la version sembrada por CC). codigo: OK / AMB / LEX / CULT / NC (ver Codebook).

Sheet Codebook
A1: Libro de codigos - codigo primario de comprension (excluyente)
A3: Codigo | B3: Etiqueta | C3: Definicion
A4: OK | B4: Comprension plena | C4: Reformula el item de forma equivalente al significado original, sin dudar ni pedir aclaracion.
A5: AMB | B5: Ambiguedad | C5: Entiende palabras sueltas pero reformula en un sentido distinto / mas estrecho o amplio; o duda entre dos interpretaciones.
A6: LEX | B6: Fallo lexical | C6: Una o mas palabras no se comprenden; pide aclaracion o declara desconocer el termino.
A7: CULT | B7: Distancia cultural | C7: Comprende el item pero lo marca como ajeno, extranjero, viejo o irreconocible en su contexto.
A8: NC | B8: No comprension total | C8: No logra reconstruir el significado ni tras una sonda neutra.
A10: Marcas secundarias (no excluyentes)
A11: m_reformulo | C11: Hubo reformulacion espontanea.
A12: m_discrepancia | C12: La respuesta en escala contradice lo verbalizado.
A13: m_tiempo | C13: Tiempo de respuesta atipico (> 2 SD del item); se completa tras el analisis.
A14: m_propone_alt | C14: El participante propuso una palabra o frase alternativa concreta.
A16: Acuerdo inter-codificador | C16: Kappa de Cohen sobre el codigo primario. Objetivo: kappa >= 0,70 aceptable; >= 0,80 bueno. Si < 0,70: revisar codebook, recalibrar y recodificar.

Sheet Log_cambios
A1: Log de cambios (pack 8.4 punto 2) - pre-cargado con 24 propuestas a priori (consenso experto)
A3: item_id | B3: dim | C3: texto_mi_proximo_paso (verificar via API) | D3: texto_es_co_propuesto_a_priori | E3: texto_es_co_post_piloto | F3: tipo_cambio | G3: justificacion | H3: fuente | I3: metrica_disparadora | J3: decision (aplicar/observar/escalar)
A4: R4 | B4: R | C4: Criar peces en una piscifactoria | D4: Criar peces en un criadero | F4: lexical | H4: consenso experto
A5: R6 | B5: R | C5: Conducir un camion para repartir paquetes a oficinas y casas | D5: Manejar un camion para entregar paquetes a oficinas y casas | F5: lexical / registro | H5: consenso experto
A6: R9 | B6: R | C6: Configurar y operar maquinas para hacer productos | D6: Poner a punto y operar maquinas para fabricar productos | F6: lexical | H6: consenso experto
A7: I1 | B7: I | C7: Desarrollar una medicina nueva | D7: Desarrollar un medicamento nuevo | F7: lexical (desambiguacion) | H7: consenso experto
A8: I9 | B8: I | C8: Inventar un reemplazo para el azucar | D8: Inventar un sustituto del azucar | F8: registro | H8: consenso experto
A9: A6 | B9: A | C9: Pintar decorados para obras de teatro | D9: Pintar escenografias para obras de teatro | F9: lexical | H9: consenso experto
A10: A8 | B10: A | C10: Bailar jazz o claque | D10: Bailar jazz o tap | F10: lexical (termino de Espana) | H10: consenso experto
A11: S3 | B11: S | C11: Dar consejeria de carrera a las personas | D11: Orientar a las personas en su carrera profesional | F11: lexical (calco) | H11: consenso experto
A12: S5 | B12: S | C12: Hacer trabajo voluntario en una organizacion sin fines de lucro | D12: Hacer trabajo voluntario en una organizacion sin animo de lucro | F12: lexical (variante regional) | H12: consenso experto
A13: S10 | B13: S | C13: Dar una clase de escuela secundaria | D13: Dictar una clase en un colegio de secundaria | F13: lexical / registro | H13: consenso experto
A14: E2 | B14: E | C14: Administrar una tienda minorista | D14: Administrar una tienda | F14: registro | H14: consenso experto
A15: E3 | B15: E | C15: Administrar un salon de belleza o una peluqueria | D15: Administrar un salon de belleza o una barberia | F15: lexical (precision) | H15: consenso experto
... A27: C8 | B27: C | C27: Registrar pagos de renta | D27: Registrar pagos de arriendo | F27: lexical (variante regional) | H27: consenso experto
A29: Columnas amarillas: completar tras el piloto. 'texto_mi_proximo_paso' es inferido; verificar el texto real via API O*NET antes del campo. Items solo de observacion (R10, I4, S9, E1) NO entran al log: no se propone cambio.

Sheet Metricas_item
A1: Metricas de comprension por item - llenar tras codificar (plan de analisis A-8)
A3: item_id | B3: dim | C3: n_validos | D3: % comprension plena | E3: % no comprension | F3: % reformulacion | G3: % distancia cultural | H3: % discrepancia | I3: mediana_tiempo_seg | J3: % tiempo atipico | K3: decision
A4: R1 | B4: R
A5: R2 | B5: R
A6: R3 | B6: R
A7: R4 | B7: R
A8: R5 | B8: R
A9: R6 | B9: R
A10: R7 | B10: R
A11: R8 | B11: R
A12: R9 | B12: R
A13: R10 | B13: R
A14: I1 | B14: I
A15: I2 | B15: I
... A63: C10 | B63: C
A65: Criterios pack 8.3: % no comprension > 20% -> re-adaptar; % reformulacion > 30% -> re-adaptar; % distancia cultural > 25% -> re-adaptar; % discrepancia > 20% -> re-adaptar.

Sheet Metricas_dimension
A1: Metricas por dimension RIASEC - alfa PROVISIONAL (N pequeno, IC amplio)
A3: dimension | B3: n_items | C3: alpha | D3: alpha IC95 inf | E3: alpha IC95 sup | F3: % comprension media
A4: Realistic (R) | B4: 10
A5: Investigative (I) | B5: 10
A6: Artistic (A) | B6: 10
A7: Social (S) | B7: 10
A8: Enterprising (E) | B8: 10
A9: Conventional (C) | B9: 10
A11: El alfa del piloto cognitivo es provisional y no decide nada irreversible. Referencia: alfa >= 0,70 deseable. La confiabilidad se confirma en la fase 2 (n=150-300).
